src/writeToReg.sv

typedef enum logic [5:0] {
		CU_LUI, CU_AUIPC, CU_JAL, CU_JALR, 
		CU_BEQ, CU_BNE, CU_BLT, CU_BGE, CU_BLTU, CU_BGEU, 
		CU_LB, CU_LH, CU_LW, CU_LBU, CU_LHU, CU_SB, CU_SH, CU_SW, 
		CU_ADDI, CU_SLTI, CU_SLTIU, CU_SLIU, CU_XORI, CU_ORI, CU_ANDI, CU_SLLI, CU_SRLI, CU_SRAI, 
		CU_ADD, CU_SUB, CU_SLL, CU_SLT, CU_SLTU, CU_XOR, CU_SRL, CU_SRA, CU_OR, CU_AND,
		CU_ERROR
	} cuOPType;	

module writeToReg (
    input logic [31:0] memload, pc, aluOut, imm,
    input logic negative,
    input logic [5:0] cuOP,
    output logic [31:0] writeData
);


always_comb begin
    case(cuOP)
        CU_LB: writeData = {{24{memload[7]}}, memload[7:0]};
        CU_LH: writeData = {{16{memload[7]}}, memload[15:0]};
        CU_LW: writeData = memload;
        CU_LBU: writeData = {24'b0, memload[7:0]};
        CU_LHU: writeData = {16'b0, memload[15:0]};
        CU_AUIPC: writeData = pc + {imm[31:12], 12'b0};
        CU_LUI: writeData = {imm[31:12], 12'b0};
        CU_JAL: writeData = pc + 4;
        CU_JALR: writeData = pc + 4;
        default: writeData = aluOut;
    endcase
end






endmodule

src/tb_writeToReg.sv

`timescale 1ms / 100us


module writeToReg_tb ();
 
typedef enum logic [5:0] {
		CU_LUI, CU_AUIPC, CU_JAL, CU_JALR, 
		CU_BEQ, CU_BNE, CU_BLT, CU_BGE, CU_BLTU, CU_BGEU, 
		CU_LB, CU_LH, CU_LW, CU_LBU, CU_LHU, CU_SB, CU_SH, CU_SW, 
		CU_ADDI, CU_SLTI, CU_SLTIU, CU_SLIU, CU_XORI, CU_ORI, CU_ANDI, CU_SLLI, CU_SRLI, CU_SRAI, 
		CU_ADD, CU_SUB, CU_SLL, CU_SLT, CU_SLTU, CU_XOR, CU_SRL, CU_SRA, CU_OR, CU_AND,
		CU_ERROR
	} cuOPType;


 
logic [31:0] tb_memload, tb_pc, tb_aluOut, tb_imm, tb_writeData;
logic tb_negative, tb_checking_outputs;
logic [5:0] tb_cuOP;
integer tb_test_num, tb_intermResult;
string tb_test_case;
 
writeToReg DUT(.memload(tb_memload), .pc(tb_pc), .aluOut(tb_aluOut),
.imm(tb_imm), .writeData(tb_writeData), .negative(tb_negative), .cuOP(tb_cuOP));
 
 
localparam CLK_PERIOD = 10;
 
logic tb_clk;
 
always begin
    tb_clk = 1'b0;
    #(CLK_PERIOD / 2.0);
    tb_clk = 1'b1;
    #(CLK_PERIOD / 2.0);
end
 
task checkOut;
    input logic [31:0] exp_out;
    tb_checking_outputs = 1'b1;
	#2;
    if(tb_writeData == exp_out)
        $info("Correct value to write %0b.", exp_out);
    else
        $error("Incorrect value to write. Expected: %0b. Actual: %0b.", exp_out, tb_writeData);
    #(1);
    tb_checking_outputs = 1'b0;  
endtask
 
initial begin
    $dumpfile("dump.vcd");
    $dumpvars;
    tb_memload = 32'b0;
    tb_pc = 32'b0;
    tb_aluOut = 32'b0;
    tb_imm = 32'b0;
    tb_negative = 0;
    tb_cuOP = 6'b0;
    tb_test_num = -1;
    tb_test_case = "Initializing";
    tb_intermResult = 0;
#2;
// ************************************************************************
  // Test Case 1: Test LB case
  // ************************************************************************
			tb_test_num += 1;
      tb_test_case = "Test Case 1: Testing LB";
	  $display("\n\n%s", tb_test_case);
			tb_memload = 32'haaaaaaaa;
			tb_pc = 32'hbbbbbbbb;
			tb_cuOP = CU_LB;
			#2;
			checkOut(32'b1111_1111_1111_1111_1111_1111_1010_1010);
			#5;
	// ************************************************************************
  // Test Case 2: Test LH case
  // ************************************************************************
			tb_test_num += 1;
      tb_test_case = "Test Case 2: Testing LH";
	  $display("\n\n%s", tb_test_case);
			tb_memload = 32'hbbbbbaba;
			tb_pc = 32'hbbbbbbbb;
			tb_cuOP = CU_LH;
			#2;
			checkOut(32'b1111_1111_1111_1111_1011_1010_1011_1010);
			#5;
	// ************************************************************************
  // Test Case 3: Test LW case
  // ************************************************************************
			tb_test_num += 1;
      tb_test_case = "Test Case 3: Testing LW";
	  $display("\n\n%s", tb_test_case);
			tb_memload = 32'habababab;
			tb_pc = 32'hbbbbbbbb;
			tb_cuOP = CU_LW;
			#2;
			checkOut(32'b1010_1011_1010_1011_1010_1011_1010_1011);
			#5;
	// ************************************************************************
  // Test Case 4: Test LBU case
  // ************************************************************************
			tb_test_num += 1;
      tb_test_case = "Test Case 4: Testing LBU";
	  $display("\n\n%s", tb_test_case);
			tb_memload = 32'haaaaaaaa;
			tb_pc = 32'hbbbbbbbb;
			tb_cuOP = CU_LBU;
			#2;
			checkOut({24'b0, 1010_1010});
			#5;
	// ************************************************************************
  // Test Case 5: Test LHU case
  // ************************************************************************
			tb_test_num += 1;
      tb_test_case = "Test Case 5: Testing LHU";
	  $display("\n\n%s", tb_test_case);
			tb_memload = 32'hbbbbbbbb;
			tb_pc = 32'hbbbbbbbb;
			tb_cuOP = CU_LHU;
			#2;
			checkOut({16'b0, 1011, 1011, 1011, 1011});
			#5;
	// ************************************************************************
  // Test Case 6: Test AUIPC case
  // ************************************************************************
			tb_test_num += 1;
      tb_test_case = "Test Case 6: Testing AUIPC";
	  $display("\n\n%s", tb_test_case);
			tb_memload = 32'hbbbbbbbb;
			tb_pc = 32'hbbbbbbbb;
			tb_imm = 32'd10;
			tb_cuOP = CU_AUIPC;
			#2;
			//check that the checkout is correct, is should the immediate be 31:12 or 19:0?
			checkOut({tb_imm[31:12], 12'b0} + tb_pc);
			#5;
	// ************************************************************************
  // Test Case 7: Test LUI case
  // ************************************************************************
			tb_test_num += 1;
      tb_test_case = "Test Case 7: Testing LUI";
	  $display("\n\n%s", tb_test_case);
			tb_memload = 32'hbbbbbbbb;
			tb_pc = 32'hbbbbbbbb;
			tb_imm = 32'd10;
			tb_cuOP = CU_LUI;
			#2;
			//check that the checkout is correct, is should the immediate be 31:12 or 19:0?
			checkOut({tb_imm[31:12], 12'b0});
			#5;
	// ************************************************************************
  // Test Case 8: Test JAL case
  // ************************************************************************
			tb_test_num += 1;
      tb_test_case = "Test Case 8: Testing JAL";
	  $display("\n\n%s", tb_test_case);
			tb_memload = 32'hbbbbbbbb;
			tb_pc = 32'hbbbbbbbb;
			tb_imm = 32'd10;
			tb_cuOP = CU_JAL;
			#2;
			//check that the checkout is correct, is should the immediate be 31:12 or 19:0?
			checkOut(tb_pc + 4);
			#5;
	// ************************************************************************
  // Test Case 9: Test JALR case
  // ************************************************************************
			tb_test_num += 1;
      tb_test_case = "Test Case 9: Testing JALR";
	  $display("\n\n%s", tb_test_case);
			tb_memload = 32'hbbbbbbbb;
			tb_pc = 32'hbbbbbbbb;
			tb_imm = 32'd10;
			tb_cuOP = CU_JALR;
			#2;
			//check that the checkout is correct, is should the immediate be 31:12 or 19:0?
			checkOut(tb_pc + 4);
			#5;
	// ************************************************************************
  // Test Case 10: Checking other OPs
  // ************************************************************************
			tb_test_num += 1;
      tb_test_case = "Test Case 10: Testing other cases";
	  $display("\n\n%s", tb_test_case);
			tb_memload = 32'hbbbbbbbb;
			tb_pc = 32'hbbbbbbbb;
			tb_imm = 32'd10;
			tb_cuOP = CU_ADD;
			#2;
			checkOut(tb_aluOut);
			#5;
			tb_cuOP = CU_XOR;
			#2;
			checkOut(tb_aluOut);
			#5;
			tb_cuOP = CU_SB;
			#2;
			checkOut(tb_aluOut);
			#5;
#1;
    $finish;
end
 
 
endmodule

dump.vcd
$date
	Tue Jun 25 19:25:03 2024
$end

$version
	Synopsys VCS version V-2023.12-SP1-1_Full64
$end

$timescale
	100us
$end

$comment Csum: 1 f82d253b83f85bfb $end


$scope module $unit $end
$upscope $end


$scope module writeToReg_tb $end
$var reg 32 ! tb_memload [31:0] $end
$var reg 32 " tb_pc [31:0] $end
$var reg 32 # tb_aluOut [31:0] $end
$var reg 32 $ tb_imm [31:0] $end
$var reg 32 % tb_writeData [31:0] $end
$var reg 1 & tb_negative $end
$var reg 1 ' tb_checking_outputs $end
$var reg 6 ( tb_cuOP [5:0] $end
$var integer 32 ) tb_test_num $end
$var integer 32 * tb_intermResult $end
$var reg 1 + tb_clk $end

$scope task checkOut $end
$var reg 32 , exp_out [31:0] $end
$upscope $end


$scope module DUT $end
$var reg 32 - memload [31:0] $end
$var reg 32 . pc [31:0] $end
$var reg 32 / aluOut [31:0] $end
$var reg 32 0 imm [31:0] $end
$var reg 1 1 negative $end
$var reg 6 2 cuOP [5:0] $end
$var reg 32 3 writeData [31:0] $end
$upscope $end

$upscope $end

$enddefinitions $end

#0
$dumpvars
01
x'
0+
0&
b00000000000000000000000000000000 /
bxxxxxxxxxxxxxxxxxxxxxxxxxxxxxxxx ,
b000000 2
b00000000000000000000000000000000 0
b00000000000000000000000000000000 -
b00000000000000000000000000000000 .
b00000000000000000000000000000000 #
b000000 (
b00000000000000000000000000000000 $
b00000000000000000000000000000000 *
b00000000000000000000000000000000 !
b00000000000000000000000000000000 "
b11111111111111111111111111111111 )
b00000000000000000000000000000000 %
b00000000000000000000000000000000 3
$end
#20
b00000000000000000000000000000000 )
b10101010101010101010101010101010 !
b10101010101010101010101010101010 -
b10111011101110111011101110111011 "
b10111011101110111011101110111011 .
b001010 (
b001010 2
b11111111111111111111111110101010 3
b11111111111111111111111110101010 %
#40
b11111111111111111111111110101010 ,
1'
#50
1+
#70
0'
#100
0+
#120
b00000000000000000000000000000001 )
b10111011101110111011101010111010 !
b10111011101110111011101010111010 -
b001011 (
b001011 2
b11111111111111111011101010111010 3
b11111111111111111011101010111010 %
#140
b11111111111111111011101010111010 ,
1'
#150
1+
#170
0'
#200
0+
#220
b00000000000000000000000000000010 )
b10101011101010111010101110101011 !
b10101011101010111010101110101011 -
b001100 (
b001100 2
b10101011101010111010101110101011 3
b10101011101010111010101110101011 %
#240
b10101011101010111010101110101011 ,
1'
#250
1+
#270
0'
#300
0+
#320
b00000000000000000000000000000011 )
b10101010101010101010101010101010 !
b10101010101010101010101010101010 -
b001101 (
b001101 2
b00000000000000000000000010101010 3
b00000000000000000000000010101010 %
#340
b00000000000000000000000010101010 ,
1'
#350
1+
#370
0'
#400
0+
#420
b00000000000000000000000000000100 )
b10111011101110111011101110111011 !
b10111011101110111011101110111011 -
b001110 (
b001110 2
b00000000000000001011101110111011 3
b00000000000000001011101110111011 %
#440
b00000000000000001011101110111011 ,
1'
#450
1+
#470
0'
#500
0+
#520
b00000000000000000000000000000101 )
b00000000000000000000000000001010 $
b00000000000000000000000000001010 0
b000001 (
b000001 2
b10111011101110111011101110111011 3
b10111011101110111011101110111011 %
#540
b10111011101110111011101110111011 ,
1'
#550
1+
#570
0'
#600
0+
#620
b00000000000000000000000000000110 )
b000000 (
b000000 2
b00000000000000000000000000000000 3
b00000000000000000000000000000000 %
#640
b00000000000000000000000000000000 ,
1'
#650
1+
#670
0'
#700
0+
#720
b00000000000000000000000000000111 )
b000010 (
b000010 2
b10111011101110111011101110111111 3
b10111011101110111011101110111111 %
#740
b10111011101110111011101110111111 ,
1'
#750
1+
#770
0'
#800
0+
#820
b00000000000000000000000000001000 )
b000011 (
b000011 2
#840
1'
#850
1+
#870
0'
#900
0+
#920
b00000000000000000000000000001001 )
b011100 (
b011100 2
b00000000000000000000000000000000 3
b00000000000000000000000000000000 %
#940
b00000000000000000000000000000000 ,
1'
#950
1+
#970
0'
#1000
0+
#1020
b100001 (
b100001 2
#1040
1'
#1050
1+
#1070
0'
#1100
0+
#1120
b001111 (
b001111 2
#1140
1'
#1150
1+
#1170
0'
