src/control.sv
	typedef enum logic [5:0] {
		CU_LUI, CU_AUIPC, CU_JAL, CU_JALR, 
		CU_BEQ, CU_BNE, CU_BLT, CU_BGE, CU_BLTU, CU_BGEU, 
		CU_LB, CU_LH, CU_LW, CU_LBU, CU_LHU, CU_SB, CU_SH, CU_SW, 
		CU_ADDI, CU_SLTI, CU_SLTIU, CU_SLIU, CU_XORI, CU_ORI, CU_ANDI, CU_SLLI, CU_SRLI, CU_SRAI, 
		CU_ADD, CU_SUB, CU_SLL, CU_SLT, CU_SLTU, CU_XOR, CU_SRL, CU_SRA, CU_OR, CU_AND,
		CU_ERROR
	} cuOPType;	

	typedef enum logic [6:0] {
		RTYPE = 7'b0110011,
		ITYPE = 7'b0010011,
		STORE = 7'b0100011,
		LOAD = 7'b0000011,
		BTYPE = 7'b1100011,
		JALR = 7'b1100111,
		JAL = 7'b1101111,
		AUIPC = 7'b0010111,
		LUI = 7'b0110111
	} opCode_t;	

	typedef enum logic [3:0] {
		ALU_ADD = 0, 
		ALU_SUB = 1,
		ALU_OR = 2, 
		ALU_XOR = 3, 
		ALU_AND = 4, 
		ALU_SLL = 5, 
		ALU_SRA = 6, 
		ALU_SLTU = 7, 
		ALU_SLT = 8,
		ALU_SRL = 9
	}aluOPType;

	typedef enum logic [2:0] {
		ADDI = 3'b000,
		SLTI = 3'b010,
		SLTIU = 3'b011,
		XORI = 3'b100,
		SLLI = 3'b001,
		SRLI = 3'b101,
		ORI = 3'b110,
		ANDI = 3'b111
	} ifunc_t;

	typedef enum logic [2:0] {
		ADD = 3'b000,
		SLL = 3'b001,
		SLT = 3'b010,
		SLTU = 3'b011,
		XOR = 3'b100,
		SRL = 3'b101,
		OR = 3'b110,
		AND = 3'b111
	} rfunc_t;


module controller(
	input logic [31:0] instruction,
	output logic [4:0] reg_1, reg_2, rd,
	output logic [19:0] imm,
	output logic [3:0] aluOP,
	output logic [5:0] cuOP,
	output logic regWrite, memWrite, memRead, aluSrc
);

always_comb begin
	reg_1 = 0;
	reg_2 = 0;
	rd = 0;
	imm = 20'b0;
	regWrite=0; 
	memWrite=0; 
	memRead=0; 
	aluSrc=0;
	casez (instruction[6:0])
	(LUI): begin
		cuOP = CU_LUI;
		imm = instruction[31:12];
		rd = instruction[11:7];
		regWrite = 1;
	end
	(AUIPC): begin
		cuOP = CU_AUIPC;
		imm = instruction[31:12];
		rd = instruction[11:7];
		regWrite = 1;
	end
	(JAL): begin
		cuOP = CU_JAL;
		imm = instruction[31:12];
		rd = instruction[11:7];
		regWrite = 1;
	end
	(JALR): begin
		cuOP = CU_JALR;
		imm = {8'b0, instruction[31:20]};
		reg_1 = instruction[19:15];
		rd = instruction[11:7];
		regWrite = 1;
	end
	(BTYPE): begin
		reg_1 = instruction[19:15];
		reg_2 = instruction[24:20];
		imm = {8'b0, instruction[31:25], instruction[11:7]};
		aluOP = ALU_SUB;
		casez(instruction[9:7])
		3'b000: cuOP = CU_BEQ;
		3'b001: cuOP = CU_BNE; 
		3'b100: cuOP = CU_BLT; 
		3'b101: cuOP = CU_BGE; 
		3'b110: cuOP = CU_BLTU; 
		3'b111: cuOP = CU_BGEU; 
		default: cuOP = CU_ERROR;
		endcase
	end
	(LOAD): begin
		reg_1 = instruction[19:15];
		rd = instruction[11:7];
		imm = {8'b0, instruction[31:25], instruction[11:7]};
		regWrite = 1;
		aluSrc = 1;
		memRead = 1;
		aluOP = ALU_ADD;
		casez(instruction[9:7])
		3'b000: cuOP = CU_LB; 
		3'b001: cuOP = CU_LH; 
		3'b010: cuOP = CU_LW; 
		3'b100: cuOP = CU_LBU; 
		3'b101: cuOP = CU_LHU; 
		default: cuOP = CU_ERROR;
		endcase
	end
	(STORE): begin
		reg_1 = instruction[19:15];
		reg_2 = instruction[24:20];
		imm = {8'b0, instruction[31:20]};
		memWrite = 1;
		aluSrc = 1;
		aluOP = ALU_ADD;
		casez(instruction[9:7])
		3'b000: cuOP = CU_SB;
		3'b001: cuOP = CU_SH;
		3'b010: cuOP = CU_SW;
		default: cuOP = CU_ERROR;
		endcase
	end
	(ITYPE): begin
		reg_1 = instruction[19:15];
		rd = instruction[11:7];
		imm = {8'b0, instruction[31:20]};
		regWrite = 1;
		aluSrc = 1;
		casez(instruction[9:7])
		ADDI: begin
			aluOP = ALU_ADD;
			cuOP = CU_ADDI;
		end
		SLTI: begin
			aluOP = ALU_SLT;
			cuOP = CU_SLTI;
		end
		SLTIU: begin
			aluOP = ALU_SLTU;
			cuOP = CU_SLTIU;
		end 
		XORI: begin
			aluOP = ALU_XOR;
			cuOP = CU_XORI;
		end 
		ORI: begin
			aluOP = ALU_OR;
			cuOP = CU_ORI;
		end 
		ANDI: begin
			aluOP = ALU_AND;
			cuOP = CU_ANDI;
		end 
		SLLI: begin
			aluOP = ALU_SLL;
			cuOP = CU_SLLI;
		end 
		SRLI: begin
			if(|instruction[31:22])begin
			aluOP = ALU_SRL;
			cuOP = CU_SRLI;
			end else begin
			aluOP = ALU_SRA;
			cuOP = CU_SRAI;
			end
		end 
		default: cuOP = CU_ERROR;
		endcase
	end
	(RTYPE): begin
		reg_1 = instruction[19:15];
		reg_2 = instruction[24:20];
		regWrite = 1;
		casez(instruction[9:7])
		ADD: begin
			if(|instruction[31:22])begin
			aluOP = ALU_ADD;
			cuOP = CU_ADD;
			end else begin
			aluOP = ALU_SUB;
			cuOP = CU_SUB;
			end
		end
		SLT: begin
			aluOP = ALU_SLT;
			cuOP = CU_SLT;
		end
		SLTU: begin
			aluOP = ALU_SLTU;
			cuOP = CU_SLTU;
		end 
		XOR: begin
			aluOP = ALU_XOR;
			cuOP = CU_XOR;
		end 
		OR: begin
			aluOP = ALU_OR;
			cuOP = CU_OR;
		end 
		AND: begin
			aluOP = ALU_AND;
			cuOP = CU_AND;
		end 
		SLL: begin
			aluOP = ALU_SLL;
			cuOP = CU_SLL;
		end 
		SRLI: begin
			if(|instruction[31:22])begin
			aluOP = ALU_SRL;
			cuOP = CU_SRL;
			end else begin
			aluOP = ALU_SRA;
			cuOP = CU_SRA;
			end
		end 
		default: cuOP = CU_ERROR;
		endcase
	end
	default: cuOP = CU_ERROR;
	endcase
end
endmodule

src/tb_control.sv
//input 32 bits imemload 
// output read_reg1, read_reg2, writeReg - 5 bits, 
// Cuop - 6 bits. 
// Aluop - 4 bits
// regwrite, Alusrc 1 bit 
// imm 20 bits 

`include "src/control.sv"

`timescale 1 ms/ 100us

module tb_control();
logic [31:0] tb_instructions;
logic [4:0] tb_reg_1, tb_reg_2, tb_rd;
logic [19:0] tb_imm;
logic [3:0] tb_aluOP;
cuOPType tb_cuOP;
logic tb_regWrite, tb_memWrite, tb_memRead, tb_aluSrc;

parameter PERIOD = 10;
controller DUT (.cuOP(tb_cuOP), .instruction(tb_instructions), 
.reg_1(tb_reg_1), .reg_2(tb_reg_2), .rd(tb_rd),
.imm(tb_imm), .aluOP(tb_aluOP), .regWrite(tb_regWrite), .memWrite(tb_memWrite), .memRead(tb_memRead), .aluSrc(tb_aluSrc));
 
    
    initial begin
    $dumpfile("dump.vcd");
    $dumpvars;

    
        tb_instructions = 32'hAAAAA537; //Lui
         #(PERIOD)
        tb_instructions = 32'hAAAAA517; // AUIPC 
         #(PERIOD)
        tb_instructions = 32'hFACEE56F;  // JAL
        #(PERIOD)
        tb_instructions = 32'hFAC78567; // JALR
        #(PERIOD)
        tb_instructions = 32'h6EDA88E7;// BEQ
        #(PERIOD)
        tb_instructions = 32'h6EDA98E7;// BNE
        #(PERIOD)
        tb_instructions = 32'h6EDAC8E7 ;// BGE
        #(PERIOD)
        tb_instructions = 32'h6EDAD8E7; // BLTU
        #(PERIOD)
        tb_instructions = 32'h6EDAE8E7; // BEGU
        #(PERIOD)
        tb_instructions = 32'h6EDAF8E7; // BGEU
        #(PERIOD)
        tb_instructions = 32'hABCA8503; // LB
        #(PERIOD)
        tb_instructions = 32'hABCA9503 ;// LH
        #(PERIOD)
        tb_instructions = 32'hABCAA503; // LW
        #(PERIOD)
        tb_instructions = 32'hABCAC503 ;// LBU
        #(PERIOD)
        tb_instructions = 32'hABCAD503; // LHU
        #(PERIOD)
        tb_instructions = 32'hEEAC0723 ;// SB
        #(PERIOD)
        tb_instructions = 32'hEEAC1723; // SH
        #(PERIOD)
        tb_instructions = 32'hEEAC2723; // SW
        #(PERIOD)
        tb_instructions = 32'hABC50D13; // ADDI
        #(PERIOD)
        tb_instructions = 32'hABC52D13; // SLTI
        #(PERIOD)
        tb_instructions = 32'hABC53D13; //SLTIU 
        #(PERIOD)
        tb_instructions = 32'hABC54D13; //XORI
        #(PERIOD)
        tb_instructions = 32'hABC56D13; //ORI
        #(PERIOD)
        tb_instructions = 32'hABC57D13; //ANDI
        #(PERIOD)
        tb_instructions = 32'h002A9C13; // SLLI
        #(PERIOD)
        tb_instructions = 32'h402D9C13; // SRLI
        #(PERIOD)
        tb_instructions = 32'h402D9C13; // SRAI
        #(PERIOD)
        tb_instructions = 32'h00C50C33; // add
        #(PERIOD)
        tb_instructions = 32'h40C50C33; // sub
        #(PERIOD)
        tb_instructions = 32'h00C51C33; // sll
        #(PERIOD)
        tb_instructions = 32'h00C52C33; // slt
        #(PERIOD)
        tb_instructions = 32'h00C53C33; // sltu
        #(PERIOD)
        tb_instructions = 32'h00C54C33; // xor
        #(PERIOD)
        tb_instructions = 32'h00C55C33; // srl
        #(PERIOD)
        tb_instructions = 32'h40C55C33; // sra
        #(PERIOD)
        tb_instructions = 32'h00C56C33; //OR
        #(PERIOD)
        tb_instructions = 32'h00C57C33; // AND

    end
endmodule

dump.vcd
$date
	Tue Jun 25 18:19:04 2024
$end

$version
	Synopsys VCS version V-2023.12-SP1-1_Full64
$end

$timescale
	100us
$end

$comment Csum: 1 c3df987106b82004 $end


$scope module $unit $end
$upscope $end


$scope module tb_control $end
$var reg 32 ! tb_instructions [31:0] $end
$var reg 5 " tb_reg_1 [4:0] $end
$var reg 5 # tb_reg_2 [4:0] $end
$var reg 5 $ tb_rd [4:0] $end
$var reg 20 % tb_imm [19:0] $end
$var reg 4 & tb_aluOP [3:0] $end
$var reg 6 ' tb_cuOP [5:0] $end
$var reg 1 ( tb_regWrite $end
$var reg 1 ) tb_memWrite $end
$var reg 1 * tb_memRead $end
$var reg 1 + tb_aluSrc $end

$scope module DUT $end
$var reg 32 , instruction [31:0] $end
$var reg 5 - reg_1 [4:0] $end
$var reg 5 . reg_2 [4:0] $end
$var reg 5 / rd [4:0] $end
$var reg 20 0 imm [19:0] $end
$var reg 4 1 aluOP [3:0] $end
$var reg 6 2 cuOP [5:0] $end
$var reg 1 3 regWrite $end
$var reg 1 4 memWrite $end
$var reg 1 5 memRead $end
$var reg 1 6 aluSrc $end
$upscope $end

$upscope $end

$enddefinitions $end

#0
$dumpvars
06
05
04
13
0+
0*
0)
1(
bxxxx 1
b000000 2
b10101010101010101010 0
b10101010101010101010010100110111 ,
b01010 /
b00000 -
b00000 .
bxxxx &
b000000 '
b10101010101010101010 %
b10101010101010101010010100110111 !
b01010 $
b00000 "
b00000 #
$end
#100
b10101010101010101010010100010111 !
b10101010101010101010010100010111 ,
b000001 2
b000001 '
#200
b11111010110011101110010101101111 !
b11111010110011101110010101101111 ,
b000010 2
b000010 '
b11111010110011101110 0
b11111010110011101110 %
#300
b11111010110001111000010101100111 !
b11111010110001111000010101100111 ,
b000011 2
b000011 '
b00000000111110101100 0
b00000000111110101100 %
b01111 -
b01111 "
#400
b01101110110110101000100011100011 !
b01101110110110101000100011100011 ,
b000100 2
b000100 '
b0001 1
b0001 &
03
0(
b00000000011011110001 0
b00000000011011110001 %
b00000 /
b00000 $
b01101 .
b01101 #
b10101 -
b10101 "
#500
b01101110110110101001100011100011 !
b01101110110110101001100011100011 ,
b000101 2
b000101 '
#600
b01101110110110101100100011100011 !
b01101110110110101100100011100011 ,
b000110 2
b000110 '
#700
b01101110110110101101100011100011 !
b01101110110110101101100011100011 ,
b000111 2
b000111 '
#800
b01101110110110101110100011100011 !
b01101110110110101110100011100011 ,
b001000 2
b001000 '
#900
b01101110110110101111100011100011 !
b01101110110110101111100011100011 ,
b001001 2
b001001 '
#1000
b10101011110010101000010100000011 !
b10101011110010101000010100000011 ,
b001010 2
b001010 '
b0000 1
b0000 &
16
1+
15
1*
13
1(
b00000000101010101010 0
b00000000101010101010 %
b01010 /
b01010 $
b00000 .
b00000 #
#1100
b10101011110010101001010100000011 !
b10101011110010101001010100000011 ,
b001011 2
b001011 '
#1200
b10101011110010101010010100000011 !
b10101011110010101010010100000011 ,
b001100 2
b001100 '
#1300
b10101011110010101100010100000011 !
b10101011110010101100010100000011 ,
b001101 2
b001101 '
#1400
b10101011110010101101010100000011 !
b10101011110010101101010100000011 ,
b001110 2
b001110 '
#1500
b11101110101011000000011100100011 !
b11101110101011000000011100100011 ,
b001111 2
b001111 '
05
0*
14
1)
03
0(
b00000000111011101010 0
b00000000111011101010 %
b00000 /
b00000 $
b01010 .
b01010 #
b11000 -
b11000 "
#1600
b11101110101011000001011100100011 !
b11101110101011000001011100100011 ,
b010000 2
b010000 '
#1700
b11101110101011000010011100100011 !
b11101110101011000010011100100011 ,
b010001 2
b010001 '
#1800
b10101011110001010000110100010011 !
b10101011110001010000110100010011 ,
b010010 2
b010010 '
04
0)
13
1(
b00000000101010111100 0
b00000000101010111100 %
b11010 /
b11010 $
b00000 .
b00000 #
b01010 -
b01010 "
#1900
b10101011110001010010110100010011 !
b10101011110001010010110100010011 ,
b010011 2
b010011 '
b1000 1
b1000 &
#2000
b10101011110001010011110100010011 !
b10101011110001010011110100010011 ,
b010100 2
b010100 '
b0111 1
b0111 &
#2100
b10101011110001010100110100010011 !
b10101011110001010100110100010011 ,
b010110 2
b010110 '
b0011 1
b0011 &
#2200
b10101011110001010110110100010011 !
b10101011110001010110110100010011 ,
b010111 2
b010111 '
b0010 1
b0010 &
#2300
b10101011110001010111110100010011 !
b10101011110001010111110100010011 ,
b011000 2
b011000 '
b0100 1
b0100 &
#2400
b00000000001010101001110000010011 !
b00000000001010101001110000010011 ,
b011001 2
b011001 '
b0101 1
b0101 &
b00000000000000000010 0
b00000000000000000010 %
b11000 /
b11000 $
b10101 -
b10101 "
#2500
b01000000001011011001110000010011 !
b01000000001011011001110000010011 ,
b00000000010000000010 0
b00000000010000000010 %
b11011 -
b11011 "
#2700
b00000000110001010000110000110011 !
b00000000110001010000110000110011 ,
b011100 2
b011100 '
b0000 1
b0000 &
06
0+
b00000000000000000000 0
b00000000000000000000 %
b00000 /
b00000 $
b01100 .
b01100 #
b01010 -
b01010 "
#2800
b01000000110001010000110000110011 !
b01000000110001010000110000110011 ,
#2900
b00000000110001010001110000110011 !
b00000000110001010001110000110011 ,
b011110 2
b011110 '
b0101 1
b0101 &
#3000
b00000000110001010010110000110011 !
b00000000110001010010110000110011 ,
b011111 2
b011111 '
b1000 1
b1000 &
#3100
b00000000110001010011110000110011 !
b00000000110001010011110000110011 ,
b100000 2
b100000 '
b0111 1
b0111 &
#3200
b00000000110001010100110000110011 !
b00000000110001010100110000110011 ,
b100001 2
b100001 '
b0011 1
b0011 &
#3300
b00000000110001010101110000110011 !
b00000000110001010101110000110011 ,
b100010 2
b100010 '
b1001 1
b1001 &
#3400
b01000000110001010101110000110011 !
b01000000110001010101110000110011 ,
#3500
b00000000110001010110110000110011 !
b00000000110001010110110000110011 ,
b100100 2
b100100 '
b0010 1
b0010 &
#3600
b00000000110001010111110000110011 !
b00000000110001010111110000110011 ,
b100101 2
b100101 '
b0100 1
b0100 &
